pywykop3/__init__.py
pywykop3/api.py
pywykop3/connector.py
pywykop3/utils.py
pywykop3-0.7.0.dist-info/LICENSE
pywykop3-0.7.0.dist-info/METADATA
pywykop3-0.7.0.dist-info/WHEEL
pywykop3-0.7.0.dist-info/top_level.txt
pywykop3-0.7.0.dist-info/RECORD
